pymispwarninglists/__init__.py
pymispwarninglists/api.py
pymispwarninglists/data/misp-warninglists/lists/akamai/list.json
pymispwarninglists/data/misp-warninglists/lists/alexa/list.json
pymispwarninglists/data/misp-warninglists/lists/alphastrike-research-nt-scanning/list.json
pymispwarninglists/data/misp-warninglists/lists/alphastrike-scanning/list.json
pymispwarninglists/data/misp-warninglists/lists/amazon-aws/list.json
pymispwarninglists/data/misp-warninglists/lists/apple/list.json
pymispwarninglists/data/misp-warninglists/lists/automated-malware-analysis/list.json
pymispwarninglists/data/misp-warninglists/lists/bank-website/list.json
pymispwarninglists/data/misp-warninglists/lists/bufferover-nt-scanning/list.json
pymispwarninglists/data/misp-warninglists/lists/captive-portals/list.json
pymispwarninglists/data/misp-warninglists/lists/censys-scanning/list.json
pymispwarninglists/data/misp-warninglists/lists/check-host-net/list.json
pymispwarninglists/data/misp-warninglists/lists/cisco_top1000/list.json
pymispwarninglists/data/misp-warninglists/lists/cisco_top10k/list.json
pymispwarninglists/data/misp-warninglists/lists/cisco_top20k/list.json
pymispwarninglists/data/misp-warninglists/lists/cisco_top5k/list.json
pymispwarninglists/data/misp-warninglists/lists/cloudflare/list.json
pymispwarninglists/data/misp-warninglists/lists/coalition-signals-intelligence-nt-scanning/list.json
pymispwarninglists/data/misp-warninglists/lists/common-contact-emails/list.json
pymispwarninglists/data/misp-warninglists/lists/common-ioc-false-positive/list.json
pymispwarninglists/data/misp-warninglists/lists/covid/list.json
pymispwarninglists/data/misp-warninglists/lists/covid-19-cyber-threat-coalition-whitelist/list.json
pymispwarninglists/data/misp-warninglists/lists/covid-19-krassi-whitelist/list.json
pymispwarninglists/data/misp-warninglists/lists/crl-hostname/list.json
pymispwarninglists/data/misp-warninglists/lists/crl-ip/list.json
pymispwarninglists-1.7.0.dist-info/METADATA
pymispwarninglists-1.7.0.dist-info/WHEEL
pymispwarninglists-1.7.0.dist-info/licenses/LICENSE
pymispwarninglists-1.7.0.dist-info/RECORD
