Metadata-Version: 2.4
Name: pymispwarninglists
Version: 1.7.0
Summary: Python API for the MISP warning lists.
License-Expression: BSD-3-Clause
License-File: LICENSE
Author: Raphaël Vinot
Author-email: raphael.vinot@circl.lu
Requires-Python: >=3.10
Classifier: Development Status :: 5 - Production/Stable
Classifier: Environment :: Console
Classifier: Intended Audience :: Science/Research
Classifier: Intended Audience :: Telecommunications Industry
Classifier: Programming Language :: Python :: 3
Classifier: Programming Language :: Python :: 3.10
Classifier: Programming Language :: Python :: 3.11
Classifier: Programming Language :: Python :: 3.12
Classifier: Programming Language :: Python :: 3.13
Classifier: Programming Language :: Python :: 3.14
Classifier: Topic :: Internet
Classifier: Topic :: Security
Provides-Extra: fetch-lists
Requires-Dist: requests (>=2.32.5) ; extra == "fetch-lists"
Project-URL: Repository, https://github.com/MISP/PyMISPWarningLists/
